MANIFEST.in
README.txt
setup.py
XStatic_Angular_Animate.egg-info/PKG-INFO
XStatic_Angular_Animate.egg-info/SOURCES.txt
XStatic_Angular_Animate.egg-info/dependency_links.txt
XStatic_Angular_Animate.egg-info/namespace_packages.txt
XStatic_Angular_Animate.egg-info/not-zip-safe
XStatic_Angular_Animate.egg-info/top_level.txt
xstatic/__init__.py
xstatic/pkg/__init__.py
xstatic/pkg/angular_animate/__init__.py
xstatic/pkg/angular_animate/data/angular-animate.js