Metadata-Version: 1.0
Name: XStatic-Angular-Animate
Version: 1.2.1.1
Summary: Angular-Animate 1.2.1 (XStatic packaging standard)
Home-page: https://angularjs.org/
Author: Maxime Vidori
Author-email: maxime.vidori@enovance.com
License: (same as Angular-Animate)
Keywords: angular_animate xstatic
Platform: any
